hammx.py
hammx-0.1.0.dist-info/METADATA
hammx-0.1.0.dist-info/WHEEL
hammx-0.1.0.dist-info/top_level.txt
hammx-0.1.0.dist-info/RECORD
