Metadata-Version: 2.4
Name: hammx
Version: 0.1.0
Summary: async rest like a boss
Author-email: Steve Ryherd <steve.ryherd@gmail.com>
Project-URL: Homepage, https://github.com/steveryherd/hammx
Project-URL: Bug Tracker, https://github.com/steveryherd/hammx/issues
Classifier: Development Status :: 4 - Beta
Classifier: Intended Audience :: Developers
Classifier: Programming Language :: Python :: 3
Classifier: Programming Language :: Python :: 3.7
Classifier: Programming Language :: Python :: 3.8
Classifier: Programming Language :: Python :: 3.9
Classifier: Programming Language :: Python :: 3.10
Classifier: Topic :: Software Development :: Libraries
Requires-Python: >=3.7
Requires-Dist: httpx>=0.18.0
Provides-Extra: dev
Requires-Dist: pytest>=7.0.0; extra == "dev"
Requires-Dist: pytest-asyncio>=0.18.0; extra == "dev"
Requires-Dist: respx>=0.19.0; extra == "dev"
